sf_baso_kontol/__init__.py
sf_baso_kontol/__main__.py
sf_baso_kontol/cli.py
sf_baso_kontol-0.2.0.dist-info/METADATA
sf_baso_kontol-0.2.0.dist-info/WHEEL
sf_baso_kontol-0.2.0.dist-info/entry_points.txt
sf_baso_kontol-0.2.0.dist-info/top_level.txt
sf_baso_kontol-0.2.0.dist-info/RECORD
