Metadata-Version: 2.1
Name: sf_baso_kontol
Version: 0.2.0
Summary: pypi test
Home-page: https://github.com/IrfanDect/baso_kontol_clis
Author: IrfanDect
Author-email: bsbdrack@gmail.com
License: MIT
Keywords: super_baso_kontol
Classifier: Intended Audience :: Developers
Classifier: Topic :: Utilities
Classifier: License :: Public Domain
Classifier: Natural Language :: English
Classifier: Operating System :: OS Independent
Classifier: Programming Language :: Python :: 3
Classifier: Programming Language :: Python :: 3.2
Classifier: Programming Language :: Python :: 3.3
Classifier: Programming Language :: Python :: 3.4
Classifier: Programming Language :: Python :: 3.5
Classifier: Programming Language :: Python :: 3.6
Requires-Dist: rich
Requires-Dist: requests
Requires-Dist: prompt-toolkit
Requires-Dist: baso-kontol
Provides-Extra: excel
Requires-Dist: openpyxl ; extra == 'excel'
